mycustompackage12345/__init__.py
mycustompackage12345/add.py
mycustompackage12345/subtract.py
mycustompackage12345/extras/__init__.py
mycustompackage12345/extras/div.py
mycustompackage12345/extras/mult.py
mycustompackage12345-0.0.1.dist-info/METADATA
mycustompackage12345-0.0.1.dist-info/WHEEL
mycustompackage12345-0.0.1.dist-info/top_level.txt
mycustompackage12345-0.0.1.dist-info/RECORD
