Metadata-Version: 2.1
Name: mycustompackage12345
Version: 0.0.1
Summary: Abhinav TP twine Testing
Home-page: UNKNOWN
Author: Abhinav
Author-email: abhinav@example.com
License: UNKNOWN
Keywords: python,mycustompackage12345
Platform: UNKNOWN
